hs_test_ht/__init__.py
hs_test_ht/apis/__init__.py
hs_test_ht/apis/market/__init__.py
hs_test_ht/apis/market/api.py
hs_test_ht-0.3.11.dist-info/METADATA
hs_test_ht-0.3.11.dist-info/WHEEL
hs_test_ht-0.3.11.dist-info/top_level.txt
hs_test_ht-0.3.11.dist-info/RECORD
