Metadata-Version: 2.1
Name: hs-test-ht
Version: 0.3.11
Summary: 恒有数，源自恒生电子的金融数据社区，提供涵盖股票、基金、债券、期权期货、港股等金融数据；提供在线预览、在线下载和在线调试等功能，提供简单高效的API接口（接口语言包括HTTP、Python、MATLAB、Java）；提供丰富的接口文档、帮助文档与社区社群运营，使得用户可以方便快捷地取用数据。
Home-page: https://udata.hs.net/home?channel_source=pypi
Author: 恒生Light云
Author-email: huhl37814@hundsun.com
License: MIT Licence
Platform: UNKNOWN
Requires-Python: >=3.0.0
Requires-Dist: pandas (>=0.25.2)
Requires-Dist: pyyaml (>=5.3.1)
Requires-Dist: requests (>=2.23.0)
